nubela_api/__init__.py
nubela_api/models/profile.py
nubela_api/models/response.py
nubela_api/person_api.py
nubela_api/py.typed
nubela_api-0.2.0.dist-info/METADATA
nubela_api-0.2.0.dist-info/WHEEL
nubela_api-0.2.0.dist-info/RECORD
