Metadata-Version: 2.1
Name: nubela-api
Version: 0.2.0
Summary: 
Author: leeparnell
Author-email: 152523161+leeparnell@users.noreply.github.com
Requires-Python: >=3.11,<4.0
Classifier: Programming Language :: Python :: 3
Classifier: Programming Language :: Python :: 3.11
Classifier: Programming Language :: Python :: 3.12
Requires-Dist: pydantic (>=2.7.3,<3.0.0)
Requires-Dist: pydantic-settings (>=2.3.4,<3.0.0)
Requires-Dist: requests (>=2.32.3,<3.0.0)
